{
  "DawJobes" :
  {
    "online" : false,
    "name" : "DawJobes",
    "at" : null,
    "companies" :
    {
      "Arple" :
      {
        "name": "Arple",
        "live": false,
        "yesterday": null,
        "today": null
      },
      "Samshung" :
      {
        "name": "Samshung",
        "live": false,
        "yesterday": null,
        "today": null
      },
      "Geggle" :
      {
        "name" : "Geggle",
        "live" : false,
        "yesterday" : null,
        "today" : null
      }
    }
  }
}