{
  "PSI-3" :
  {
    "online" : false,
    "name" : "PSI-3",
    "at" : null,
    "companies" :
    {
      "SONAC" :
      {
        "name": "SONAC",
        "live": false,
        "yesterday": null,
        "today": null
      },
      "JeriamoMarts" :
      {
        "name": "JeriamoMarts",
        "live": false,
        "yesterday": null,
        "today": null
      },
      "MotaAngil" :
      {
        "name" : "MotaAngil",
        "live" : false,
        "yesterday" : null,
        "today" : null
      }
    }
  }
}